loglet.py
loglet.sh
setup.py
Loglet.egg-info/PKG-INFO
Loglet.egg-info/SOURCES.txt
Loglet.egg-info/dependency_links.txt
Loglet.egg-info/top_level.txt
loglet.egg-info/SOURCES.txt