Metadata-Version: 1.0
Name: loglet
Version: 1.0
Summary: client library Loglet, the Web-based logging system
Home-page: http://loglet.radbox.org/
Author: Adrian Sampson
Author-email: adrian@radbox.org
License: UNKNOWN
Platform: UNKNOWN
Classifier: Development Status :: 5 - Production/Stable
Classifier: Intended Audience :: Developers
Classifier: License :: OSI Approved :: MIT License
Classifier: Operating System :: OS Independent
Classifier: Programming Language :: Python :: 2.5
Classifier: Programming Language :: Python :: 2.6
Classifier: Programming Language :: Python :: 2.7
Classifier: Programming Language :: Python :: 2 :: Only
Classifier: Topic :: System :: Logging
